backscatter/__init__.py
backscatter/cli/__init__.py
backscatter/cli/client.py
backscatter/core/__init__.py
backscatter/core/fetch.py
backscatter/core/interface.py
backscatter/core/observations.py
backscatter/utils/__init__.py
backscatter-0.2.4.dist-info/LICENSE
backscatter-0.2.4.dist-info/METADATA
backscatter-0.2.4.dist-info/WHEEL
backscatter-0.2.4.dist-info/entry_points.txt
backscatter-0.2.4.dist-info/top_level.txt
backscatter-0.2.4.dist-info/RECORD
