Metadata-Version: 1.1
Name: backscatter
Version: 0.2.4
Summary: Client to interact with Backscatter.io services.
Home-page: https://backscatter.io
Author: Brandon Dixon
Author-email: brandon@backscatter.io
License: MIT
Download-URL: https://github.com/backscatterio/python/archive/master.zip
Keywords: internet scanning,cybersecurity,defense,intelligence
Platform: UNKNOWN
Classifier: Development Status :: 4 - Beta
Classifier: Intended Audience :: Developers
Classifier: License :: OSI Approved :: MIT License
Classifier: Natural Language :: English
Classifier: Programming Language :: Python
Classifier: Topic :: Software Development :: Libraries
Classifier: Topic :: Security
